hank/__init__.py
hank/dog.py
hank-0.1.7.dist-info/METADATA
hank-0.1.7.dist-info/WHEEL
hank-0.1.7.dist-info/top_level.txt
hank-0.1.7.dist-info/RECORD
