Metadata-Version: 2.4
Name: hank
Version: 0.1.7
Summary: A fun little package inspired by a very good dog named Hank.
Author-email: Daron Prater <praterdaron513@gmail.com>
License: MIT
Requires-Python: >=3.8
Requires-Dist: numpy>=1.24
Requires-Dist: pandas>=2.0
Provides-Extra: dev
Requires-Dist: pytest; extra == "dev"
Requires-Dist: pre-commit; extra == "dev"
Requires-Dist: bump2version; extra == "dev"
Requires-Dist: build; extra == "dev"
Requires-Dist: twine; extra == "dev"
Requires-Dist: black; extra == "dev"
Requires-Dist: flake8; extra == "dev"
Requires-Dist: mypy; extra == "dev"
Requires-Dist: pandas-stubs; extra == "dev"
